<?xml version="1.0" encoding="UTF-8" standalone="no"?>
<Price_List Username="proauto" Password="pwproauto" Created="07-06-2011 00:09:41">
  <car_make car_make_name="mitsubishi">
    <car_model car_model_name="&#xD;&#xA;									Anhængertræk mitsubishi Space-Wagon&#xD;&#xA;								">
      <car_models_to_spare_part_prices>
        <Spare_Part_Price price_inc_vat="1403" supplier_part_number="018-442" name="&#xD;&#xA;						018-442 &amp;nbsp; Anhængertræk til MITSUBISHI  Space-Wagon MPV  5/92 - 9/98&#xD;&#xA;					" description="&#xD;&#xA;						Trækanordning: Standard fast kuglesystemD-værdi: 9.60Udskæring i kofanger synlig&#xD;&#xA;					&#xD;&#xA;						Maks. trækvægt / lodret belastning: 1800 / 90Monteringstid anh.træk A  - op til 1 time" spare_part_category_free_text=" -  - " />
        <Spare_Part_Price price_inc_vat="525" supplier_part_number="009-148" name="&#xD;&#xA;						009-148 &amp;nbsp; Kabelsæt til MITSUBISHI  Space-Wagon MPV  5/92 - 9/98&#xD;&#xA;					" description="&#xD;&#xA;						Polaritet = 7-poletStik&#xD;&#xA;						Monteringstid kabelsæt S - op til 30 min." spare_part_category_free_text=" -  - " />
        <Spare_Part_Price price_inc_vat="1403" supplier_part_number="022-801" name="&#xD;&#xA;						022-801 &amp;nbsp; Anhængertræk til MITSUBISHI  Space-Wagon MPV  10/98 - 03&#xD;&#xA;					" description="&#xD;&#xA;						Trækanordning: Standard fast kuglesystemD-værdi: 10.00&#xD;&#xA;					&#xD;&#xA;						Maks. trækvægt / lodret belastning: 1800 / 80Monteringstid anh.træk A  - op til 1 time" spare_part_category_free_text=" -  - " />
        <Spare_Part_Price price_inc_vat="583" supplier_part_number="010-008" name="&#xD;&#xA;						010-008 &amp;nbsp; Kabelsæt til MITSUBISHI  Space-Wagon MPV  10/98 - 03&#xD;&#xA;					" description="&#xD;&#xA;						Polaritet = 7-poletStik&#xD;&#xA;						Monteringstid kabelsæt S - op til 30 min." spare_part_category_free_text=" -  - " />
      </car_models_to_spare_part_prices>
    </car_model>
  </car_make>
</Price_List>